{
  "indexes": [
    {
      "collectionGroup": "battles",
      "queryScope": "COLLECTION",
      "fields": [
        { "fieldPath": "status", "order": "ASCENDING" },
        { "fieldPath": "created_at", "order": "DESCENDING" }
      ]
    },
    {
      "collectionGroup": "reactions",
      "queryScope": "COLLECTION",
      "fields": [
        { "fieldPath": "battle_id", "order": "ASCENDING" },
        { "fieldPath": "created_at", "order": "DESCENDING" }
      ]
    },
    {
      "collectionGroup": "votes",
      "queryScope": "COLLECTION",
      "fields": [
        { "fieldPath": "battle_id", "order": "ASCENDING" },
        { "fieldPath": "created_at", "order": "DESCENDING" }
      ]
    },
    {
      "collectionGroup": "gladiators",
      "queryScope": "COLLECTION",
      "fields": [
        { "fieldPath": "wins", "order": "DESCENDING" },
        { "fieldPath": "createdAt", "order": "DESCENDING" }
      ]
    },
    {
      "collectionGroup": "battle_history",
      "queryScope": "COLLECTION",
      "fields": [
        { "fieldPath": "winner", "order": "ASCENDING" },
        { "fieldPath": "created_at", "order": "DESCENDING" }
      ]
    }
  ],
  "fieldOverrides": []
}
